sqlalchemy_commons/__init__.py
sqlalchemy_commons/models.py
sqlalchemy_commons-0.0.2.dist-info/LICENSE.txt
sqlalchemy_commons-0.0.2.dist-info/METADATA
sqlalchemy_commons-0.0.2.dist-info/RECORD
sqlalchemy_commons-0.0.2.dist-info/WHEEL
sqlalchemy_commons-0.0.2.dist-info/top_level.txt
